{"type":"Program","start":0,"end":3011,"loc":{"start":{"line":1,"column":0},"end":{"line":42,"column":0}},"body":[{"type":"VariableDeclaration","start":0,"end":31,"loc":{"start":{"line":1,"column":0},"end":{"line":1,"column":31}},"declarations":[{"type":"VariableDeclarator","start":6,"end":31,"loc":{"start":{"line":1,"column":6},"end":{"line":1,"column":31}},"id":{"type":"ObjectPattern","start":6,"end":11,"loc":{"start":{"line":1,"column":6},"end":{"line":1,"column":11}},"properties":[{"type":"Property","start":8,"end":9,"loc":{"start":{"line":1,"column":8},"end":{"line":1,"column":9}},"method":false,"shorthand":true,"computed":false,"key":{"type":"Identifier","start":8,"end":9,"loc":{"start":{"line":1,"column":8},"end":{"line":1,"column":9}},"name":"h"},"kind":"init","value":{"type":"Identifier","start":8,"end":9,"loc":{"start":{"line":1,"column":8},"end":{"line":1,"column":9}},"name":"h"}}]},"init":{"type":"CallExpression","start":14,"end":31,"loc":{"start":{"line":1,"column":14},"end":{"line":1,"column":31}},"callee":{"type":"Identifier","start":14,"end":21,"loc":{"start":{"line":1,"column":14},"end":{"line":1,"column":21}},"name":"require"},"arguments":[{"type":"Literal","start":22,"end":30,"loc":{"start":{"line":1,"column":22},"end":{"line":1,"column":30}},"value":"preact","raw":"'preact'"}]}}],"kind":"const"},{"type":"FunctionDeclaration","start":33,"end":904,"loc":{"start":{"line":3,"column":0},"end":{"line":9,"column":1}},"id":{"type":"Identifier","start":42,"end":50,"loc":{"start":{"line":3,"column":9},"end":{"line":3,"column":17}},"name":"FileIcon"},"expression":false,"generator":false,"async":false,"params":[],"body":{"type":"BlockStatement","start":54,"end":904,"loc":{"start":{"line":3,"column":21},"end":{"line":9,"column":1}},"body":[{"type":"ReturnStatement","start":58,"end":902,"loc":{"start":{"line":4,"column":2},"end":{"line":8,"column":3}},"argument":{"type":"JSXElement","start":71,"end":898,"loc":{"start":{"line":5,"column":4},"end":{"line":7,"column":10}},"openingElement":{"type":"JSXOpeningElement","start":71,"end":178,"loc":{"start":{"line":5,"column":4},"end":{"line":5,"column":111}},"attributes":[{"type":"JSXAttribute","start":76,"end":94,"loc":{"start":{"line":5,"column":9},"end":{"line":5,"column":27}},"name":{"type":"JSXIdentifier","start":76,"end":87,"loc":{"start":{"line":5,"column":9},"end":{"line":5,"column":20}},"name":"aria-hidden"},"value":{"type":"Literal","start":88,"end":94,"loc":{"start":{"line":5,"column":21},"end":{"line":5,"column":27}},"value":"true","raw":"\"true\""}},{"type":"JSXAttribute","start":95,"end":112,"loc":{"start":{"line":5,"column":28},"end":{"line":5,"column":45}},"name":{"type":"JSXIdentifier","start":95,"end":104,"loc":{"start":{"line":5,"column":28},"end":{"line":5,"column":37}},"name":"focusable"},"value":{"type":"Literal","start":105,"end":112,"loc":{"start":{"line":5,"column":38},"end":{"line":5,"column":45}},"value":"false","raw":"\"false\""}},{"type":"JSXAttribute","start":113,"end":132,"loc":{"start":{"line":5,"column":46},"end":{"line":5,"column":65}},"name":{"type":"JSXIdentifier","start":113,"end":118,"loc":{"start":{"line":5,"column":46},"end":{"line":5,"column":51}},"name":"class"},"value":{"type":"Literal","start":119,"end":132,"loc":{"start":{"line":5,"column":52},"end":{"line":5,"column":65}},"value":"uppy-c-icon","raw":"\"uppy-c-icon\""}},{"type":"JSXAttribute","start":133,"end":143,"loc":{"start":{"line":5,"column":66},"end":{"line":5,"column":76}},"name":{"type":"JSXIdentifier","start":133,"end":138,"loc":{"start":{"line":5,"column":66},"end":{"line":5,"column":71}},"name":"width"},"value":{"type":"JSXExpressionContainer","start":139,"end":143,"loc":{"start":{"line":5,"column":72},"end":{"line":5,"column":76}},"expression":{"type":"Literal","start":140,"end":142,"loc":{"start":{"line":5,"column":73},"end":{"line":5,"column":75}},"value":11,"raw":"11"}}},{"type":"JSXAttribute","start":144,"end":157,"loc":{"start":{"line":5,"column":77},"end":{"line":5,"column":90}},"name":{"type":"JSXIdentifier","start":144,"end":150,"loc":{"start":{"line":5,"column":77},"end":{"line":5,"column":83}},"name":"height"},"value":{"type":"JSXExpressionContainer","start":151,"end":157,"loc":{"start":{"line":5,"column":84},"end":{"line":5,"column":90}},"expression":{"type":"Literal","start":152,"end":156,"loc":{"start":{"line":5,"column":85},"end":{"line":5,"column":89}},"value":14.5,"raw":"14.5"}}},{"type":"JSXAttribute","start":158,"end":177,"loc":{"start":{"line":5,"column":91},"end":{"line":5,"column":110}},"name":{"type":"JSXIdentifier","start":158,"end":165,"loc":{"start":{"line":5,"column":91},"end":{"line":5,"column":98}},"name":"viewBox"},"value":{"type":"Literal","start":166,"end":177,"loc":{"start":{"line":5,"column":99},"end":{"line":5,"column":110}},"value":"0 0 44 58","raw":"\"0 0 44 58\""}}],"name":{"type":"JSXIdentifier","start":72,"end":75,"loc":{"start":{"line":5,"column":5},"end":{"line":5,"column":8}},"name":"svg"},"selfClosing":false},"closingElement":{"type":"JSXClosingElement","start":892,"end":898,"loc":{"start":{"line":7,"column":4},"end":{"line":7,"column":10}},"name":{"type":"JSXIdentifier","start":894,"end":897,"loc":{"start":{"line":7,"column":6},"end":{"line":7,"column":9}},"name":"svg"}},"children":[{"type":"JSXText","start":178,"end":185,"loc":{"start":{"line":5,"column":111},"end":{"line":6,"column":6}},"value":"\n      ","raw":"\n      "},{"type":"JSXElement","start":185,"end":887,"loc":{"start":{"line":6,"column":6},"end":{"line":6,"column":708}},"openingElement":{"type":"JSXOpeningElement","start":185,"end":887,"loc":{"start":{"line":6,"column":6},"end":{"line":6,"column":708}},"attributes":[{"type":"JSXAttribute","start":191,"end":884,"loc":{"start":{"line":6,"column":12},"end":{"line":6,"column":705}},"name":{"type":"JSXIdentifier","start":191,"end":192,"loc":{"start":{"line":6,"column":12},"end":{"line":6,"column":13}},"name":"d"},"value":{"type":"Literal","start":193,"end":884,"loc":{"start":{"line":6,"column":14},"end":{"line":6,"column":705}},"value":"M27.437.517a1 1 0 0 0-.094.03H4.25C2.037.548.217 2.368.217 4.58v48.405c0 2.212 1.82 4.03 4.03 4.03H39.03c2.21 0 4.03-1.818 4.03-4.03V15.61a1 1 0 0 0-.03-.28 1 1 0 0 0 0-.093 1 1 0 0 0-.03-.032 1 1 0 0 0 0-.03 1 1 0 0 0-.032-.063 1 1 0 0 0-.03-.063 1 1 0 0 0-.032 0 1 1 0 0 0-.03-.063 1 1 0 0 0-.032-.03 1 1 0 0 0-.03-.063 1 1 0 0 0-.063-.062l-14.593-14a1 1 0 0 0-.062-.062A1 1 0 0 0 28 .708a1 1 0 0 0-.374-.157 1 1 0 0 0-.156 0 1 1 0 0 0-.03-.03l-.003-.003zM4.25 2.547h22.218v9.97c0 2.21 1.82 4.03 4.03 4.03h10.564v36.438a2.02 2.02 0 0 1-2.032 2.032H4.25c-1.13 0-2.032-.9-2.032-2.032V4.58c0-1.13.902-2.032 2.03-2.032zm24.218 1.345l10.375 9.937.75.718H30.5c-1.13 0-2.032-.9-2.032-2.03V3.89z","raw":"\"M27.437.517a1 1 0 0 0-.094.03H4.25C2.037.548.217 2.368.217 4.58v48.405c0 2.212 1.82 4.03 4.03 4.03H39.03c2.21 0 4.03-1.818 4.03-4.03V15.61a1 1 0 0 0-.03-.28 1 1 0 0 0 0-.093 1 1 0 0 0-.03-.032 1 1 0 0 0 0-.03 1 1 0 0 0-.032-.063 1 1 0 0 0-.03-.063 1 1 0 0 0-.032 0 1 1 0 0 0-.03-.063 1 1 0 0 0-.032-.03 1 1 0 0 0-.03-.063 1 1 0 0 0-.063-.062l-14.593-14a1 1 0 0 0-.062-.062A1 1 0 0 0 28 .708a1 1 0 0 0-.374-.157 1 1 0 0 0-.156 0 1 1 0 0 0-.03-.03l-.003-.003zM4.25 2.547h22.218v9.97c0 2.21 1.82 4.03 4.03 4.03h10.564v36.438a2.02 2.02 0 0 1-2.032 2.032H4.25c-1.13 0-2.032-.9-2.032-2.032V4.58c0-1.13.902-2.032 2.03-2.032zm24.218 1.345l10.375 9.937.75.718H30.5c-1.13 0-2.032-.9-2.032-2.03V3.89z\""}}],"name":{"type":"JSXIdentifier","start":186,"end":190,"loc":{"start":{"line":6,"column":7},"end":{"line":6,"column":11}},"name":"path"},"selfClosing":true},"closingElement":null,"children":[]},{"type":"JSXText","start":887,"end":892,"loc":{"start":{"line":6,"column":708},"end":{"line":7,"column":4}},"value":"\n    ","raw":"\n    "}]}}]}},{"type":"FunctionDeclaration","start":906,"end":2158,"loc":{"start":{"line":11,"column":0},"end":{"line":17,"column":1}},"id":{"type":"Identifier","start":915,"end":925,"loc":{"start":{"line":11,"column":9},"end":{"line":11,"column":19}},"name":"FolderIcon"},"expression":false,"generator":false,"async":false,"params":[],"body":{"type":"BlockStatement","start":929,"end":2158,"loc":{"start":{"line":11,"column":23},"end":{"line":17,"column":1}},"body":[{"type":"ReturnStatement","start":933,"end":2156,"loc":{"start":{"line":12,"column":2},"end":{"line":16,"column":3}},"argument":{"type":"JSXElement","start":946,"end":2152,"loc":{"start":{"line":13,"column":4},"end":{"line":15,"column":10}},"openingElement":{"type":"JSXOpeningElement","start":946,"end":1076,"loc":{"start":{"line":13,"column":4},"end":{"line":13,"column":134}},"attributes":[{"type":"JSXAttribute","start":951,"end":969,"loc":{"start":{"line":13,"column":9},"end":{"line":13,"column":27}},"name":{"type":"JSXIdentifier","start":951,"end":962,"loc":{"start":{"line":13,"column":9},"end":{"line":13,"column":20}},"name":"aria-hidden"},"value":{"type":"Literal","start":963,"end":969,"loc":{"start":{"line":13,"column":21},"end":{"line":13,"column":27}},"value":"true","raw":"\"true\""}},{"type":"JSXAttribute","start":970,"end":987,"loc":{"start":{"line":13,"column":28},"end":{"line":13,"column":45}},"name":{"type":"JSXIdentifier","start":970,"end":979,"loc":{"start":{"line":13,"column":28},"end":{"line":13,"column":37}},"name":"focusable"},"value":{"type":"Literal","start":980,"end":987,"loc":{"start":{"line":13,"column":38},"end":{"line":13,"column":45}},"value":"false","raw":"\"false\""}},{"type":"JSXAttribute","start":988,"end":1007,"loc":{"start":{"line":13,"column":46},"end":{"line":13,"column":65}},"name":{"type":"JSXIdentifier","start":988,"end":993,"loc":{"start":{"line":13,"column":46},"end":{"line":13,"column":51}},"name":"class"},"value":{"type":"Literal","start":994,"end":1007,"loc":{"start":{"line":13,"column":52},"end":{"line":13,"column":65}},"value":"uppy-c-icon","raw":"\"uppy-c-icon\""}},{"type":"JSXAttribute","start":1008,"end":1045,"loc":{"start":{"line":13,"column":66},"end":{"line":13,"column":103}},"name":{"type":"JSXIdentifier","start":1008,"end":1013,"loc":{"start":{"line":13,"column":66},"end":{"line":13,"column":71}},"name":"style"},"value":{"type":"JSXExpressionContainer","start":1014,"end":1045,"loc":{"start":{"line":13,"column":72},"end":{"line":13,"column":103}},"expression":{"type":"ObjectExpression","start":1015,"end":1044,"loc":{"start":{"line":13,"column":73},"end":{"line":13,"column":102}},"properties":[{"type":"Property","start":1017,"end":1026,"loc":{"start":{"line":13,"column":75},"end":{"line":13,"column":84}},"method":false,"shorthand":false,"computed":false,"key":{"type":"Identifier","start":1017,"end":1022,"loc":{"start":{"line":13,"column":75},"end":{"line":13,"column":80}},"name":"width"},"value":{"type":"Literal","start":1024,"end":1026,"loc":{"start":{"line":13,"column":82},"end":{"line":13,"column":84}},"value":16,"raw":"16"},"kind":"init"},{"type":"Property","start":1028,"end":1042,"loc":{"start":{"line":13,"column":86},"end":{"line":13,"column":100}},"method":false,"shorthand":false,"computed":false,"key":{"type":"Identifier","start":1028,"end":1039,"loc":{"start":{"line":13,"column":86},"end":{"line":13,"column":97}},"name":"marginRight"},"value":{"type":"Literal","start":1041,"end":1042,"loc":{"start":{"line":13,"column":99},"end":{"line":13,"column":100}},"value":3,"raw":"3"},"kind":"init"}]}}},{"type":"JSXAttribute","start":1046,"end":1075,"loc":{"start":{"line":13,"column":104},"end":{"line":13,"column":133}},"name":{"type":"JSXIdentifier","start":1046,"end":1053,"loc":{"start":{"line":13,"column":104},"end":{"line":13,"column":111}},"name":"viewBox"},"value":{"type":"Literal","start":1054,"end":1075,"loc":{"start":{"line":13,"column":112},"end":{"line":13,"column":133}},"value":"0 0 276.157 276.157","raw":"\"0 0 276.157 276.157\""}}],"name":{"type":"JSXIdentifier","start":947,"end":950,"loc":{"start":{"line":13,"column":5},"end":{"line":13,"column":8}},"name":"svg"},"selfClosing":false},"closingElement":{"type":"JSXClosingElement","start":2146,"end":2152,"loc":{"start":{"line":15,"column":4},"end":{"line":15,"column":10}},"name":{"type":"JSXIdentifier","start":2148,"end":2151,"loc":{"start":{"line":15,"column":6},"end":{"line":15,"column":9}},"name":"svg"}},"children":[{"type":"JSXText","start":1076,"end":1083,"loc":{"start":{"line":13,"column":134},"end":{"line":14,"column":6}},"value":"\n      ","raw":"\n      "},{"type":"JSXElement","start":1083,"end":2141,"loc":{"start":{"line":14,"column":6},"end":{"line":14,"column":1064}},"openingElement":{"type":"JSXOpeningElement","start":1083,"end":2141,"loc":{"start":{"line":14,"column":6},"end":{"line":14,"column":1064}},"attributes":[{"type":"JSXAttribute","start":1089,"end":2138,"loc":{"start":{"line":14,"column":12},"end":{"line":14,"column":1061}},"name":{"type":"JSXIdentifier","start":1089,"end":1090,"loc":{"start":{"line":14,"column":12},"end":{"line":14,"column":13}},"name":"d"},"value":{"type":"Literal","start":1091,"end":2138,"loc":{"start":{"line":14,"column":14},"end":{"line":14,"column":1061}},"value":"M273.08 101.378c-3.3-4.65-8.86-7.32-15.254-7.32h-24.34V67.59c0-10.2-8.3-18.5-18.5-18.5h-85.322c-3.63 0-9.295-2.875-11.436-5.805l-6.386-8.735c-4.982-6.814-15.104-11.954-23.546-11.954H58.73c-9.292 0-18.638 6.608-21.737 15.372l-2.033 5.752c-.958 2.71-4.72 5.37-7.596 5.37H18.5C8.3 49.09 0 57.39 0 67.59v167.07c0 .886.16 1.73.443 2.52.152 3.306 1.18 6.424 3.053 9.064 3.3 4.652 8.86 7.32 15.255 7.32h188.487c11.395 0 23.27-8.425 27.035-19.18l40.677-116.188c2.11-6.035 1.43-12.164-1.87-16.816zM18.5 64.088h8.864c9.295 0 18.64-6.607 21.738-15.37l2.032-5.75c.96-2.712 4.722-5.373 7.597-5.373h29.565c3.63 0 9.295 2.876 11.437 5.806l6.386 8.735c4.982 6.815 15.104 11.954 23.546 11.954h85.322c1.898 0 3.5 1.602 3.5 3.5v26.47H69.34c-11.395 0-23.27 8.423-27.035 19.178L15 191.23V67.59c0-1.898 1.603-3.5 3.5-3.5zm242.29 49.15l-40.676 116.188c-1.674 4.78-7.812 9.135-12.877 9.135H18.75c-1.447 0-2.576-.372-3.02-.997-.442-.625-.422-1.814.057-3.18l40.677-116.19c1.674-4.78 7.812-9.134 12.877-9.134h188.487c1.448 0 2.577.372 3.02.997.443.625.423 1.814-.056 3.18z","raw":"\"M273.08 101.378c-3.3-4.65-8.86-7.32-15.254-7.32h-24.34V67.59c0-10.2-8.3-18.5-18.5-18.5h-85.322c-3.63 0-9.295-2.875-11.436-5.805l-6.386-8.735c-4.982-6.814-15.104-11.954-23.546-11.954H58.73c-9.292 0-18.638 6.608-21.737 15.372l-2.033 5.752c-.958 2.71-4.72 5.37-7.596 5.37H18.5C8.3 49.09 0 57.39 0 67.59v167.07c0 .886.16 1.73.443 2.52.152 3.306 1.18 6.424 3.053 9.064 3.3 4.652 8.86 7.32 15.255 7.32h188.487c11.395 0 23.27-8.425 27.035-19.18l40.677-116.188c2.11-6.035 1.43-12.164-1.87-16.816zM18.5 64.088h8.864c9.295 0 18.64-6.607 21.738-15.37l2.032-5.75c.96-2.712 4.722-5.373 7.597-5.373h29.565c3.63 0 9.295 2.876 11.437 5.806l6.386 8.735c4.982 6.815 15.104 11.954 23.546 11.954h85.322c1.898 0 3.5 1.602 3.5 3.5v26.47H69.34c-11.395 0-23.27 8.423-27.035 19.178L15 191.23V67.59c0-1.898 1.603-3.5 3.5-3.5zm242.29 49.15l-40.676 116.188c-1.674 4.78-7.812 9.135-12.877 9.135H18.75c-1.447 0-2.576-.372-3.02-.997-.442-.625-.422-1.814.057-3.18l40.677-116.19c1.674-4.78 7.812-9.134 12.877-9.134h188.487c1.448 0 2.577.372 3.02.997.443.625.423 1.814-.056 3.18z\""}}],"name":{"type":"JSXIdentifier","start":1084,"end":1088,"loc":{"start":{"line":14,"column":7},"end":{"line":14,"column":11}},"name":"path"},"selfClosing":true},"closingElement":null,"children":[]},{"type":"JSXText","start":2141,"end":2146,"loc":{"start":{"line":14,"column":1064},"end":{"line":15,"column":4}},"value":"\n    ","raw":"\n    "}]}}]}},{"type":"FunctionDeclaration","start":2160,"end":2698,"loc":{"start":{"line":19,"column":0},"end":{"line":26,"column":1}},"id":{"type":"Identifier","start":2169,"end":2178,"loc":{"start":{"line":19,"column":9},"end":{"line":19,"column":18}},"name":"VideoIcon"},"expression":false,"generator":false,"async":false,"params":[],"body":{"type":"BlockStatement","start":2182,"end":2698,"loc":{"start":{"line":19,"column":22},"end":{"line":26,"column":1}},"body":[{"type":"ReturnStatement","start":2186,"end":2696,"loc":{"start":{"line":20,"column":2},"end":{"line":25,"column":3}},"argument":{"type":"JSXElement","start":2199,"end":2692,"loc":{"start":{"line":21,"column":4},"end":{"line":24,"column":10}},"openingElement":{"type":"JSXOpeningElement","start":2199,"end":2261,"loc":{"start":{"line":21,"column":4},"end":{"line":21,"column":66}},"attributes":[{"type":"JSXAttribute","start":2204,"end":2222,"loc":{"start":{"line":21,"column":9},"end":{"line":21,"column":27}},"name":{"type":"JSXIdentifier","start":2204,"end":2215,"loc":{"start":{"line":21,"column":9},"end":{"line":21,"column":20}},"name":"aria-hidden"},"value":{"type":"Literal","start":2216,"end":2222,"loc":{"start":{"line":21,"column":21},"end":{"line":21,"column":27}},"value":"true","raw":"\"true\""}},{"type":"JSXAttribute","start":2223,"end":2240,"loc":{"start":{"line":21,"column":28},"end":{"line":21,"column":45}},"name":{"type":"JSXIdentifier","start":2223,"end":2232,"loc":{"start":{"line":21,"column":28},"end":{"line":21,"column":37}},"name":"focusable"},"value":{"type":"Literal","start":2233,"end":2240,"loc":{"start":{"line":21,"column":38},"end":{"line":21,"column":45}},"value":"false","raw":"\"false\""}},{"type":"JSXAttribute","start":2241,"end":2260,"loc":{"start":{"line":21,"column":46},"end":{"line":21,"column":65}},"name":{"type":"JSXIdentifier","start":2241,"end":2248,"loc":{"start":{"line":21,"column":46},"end":{"line":21,"column":53}},"name":"viewBox"},"value":{"type":"Literal","start":2249,"end":2260,"loc":{"start":{"line":21,"column":54},"end":{"line":21,"column":65}},"value":"0 0 58 58","raw":"\"0 0 58 58\""}}],"name":{"type":"JSXIdentifier","start":2200,"end":2203,"loc":{"start":{"line":21,"column":5},"end":{"line":21,"column":8}},"name":"svg"},"selfClosing":false},"closingElement":{"type":"JSXClosingElement","start":2686,"end":2692,"loc":{"start":{"line":24,"column":4},"end":{"line":24,"column":10}},"name":{"type":"JSXIdentifier","start":2688,"end":2691,"loc":{"start":{"line":24,"column":6},"end":{"line":24,"column":9}},"name":"svg"}},"children":[{"type":"JSXText","start":2261,"end":2268,"loc":{"start":{"line":21,"column":66},"end":{"line":22,"column":6}},"value":"\n      ","raw":"\n      "},{"type":"JSXElement","start":2268,"end":2445,"loc":{"start":{"line":22,"column":6},"end":{"line":22,"column":183}},"openingElement":{"type":"JSXOpeningElement","start":2268,"end":2445,"loc":{"start":{"line":22,"column":6},"end":{"line":22,"column":183}},"attributes":[{"type":"JSXAttribute","start":2274,"end":2442,"loc":{"start":{"line":22,"column":12},"end":{"line":22,"column":180}},"name":{"type":"JSXIdentifier","start":2274,"end":2275,"loc":{"start":{"line":22,"column":12},"end":{"line":22,"column":13}},"name":"d"},"value":{"type":"Literal","start":2276,"end":2442,"loc":{"start":{"line":22,"column":14},"end":{"line":22,"column":180}},"value":"M36.537 28.156l-11-7a1.005 1.005 0 0 0-1.02-.033C24.2 21.3 24 21.635 24 22v14a1 1 0 0 0 1.537.844l11-7a1.002 1.002 0 0 0 0-1.688zM26 34.18V23.82L34.137 29 26 34.18z","raw":"\"M36.537 28.156l-11-7a1.005 1.005 0 0 0-1.02-.033C24.2 21.3 24 21.635 24 22v14a1 1 0 0 0 1.537.844l11-7a1.002 1.002 0 0 0 0-1.688zM26 34.18V23.82L34.137 29 26 34.18z\""}}],"name":{"type":"JSXIdentifier","start":2269,"end":2273,"loc":{"start":{"line":22,"column":7},"end":{"line":22,"column":11}},"name":"path"},"selfClosing":true},"closingElement":null,"children":[]},{"type":"JSXText","start":2445,"end":2452,"loc":{"start":{"line":22,"column":183},"end":{"line":23,"column":6}},"value":"\n      ","raw":"\n      "},{"type":"JSXElement","start":2452,"end":2681,"loc":{"start":{"line":23,"column":6},"end":{"line":23,"column":235}},"openingElement":{"type":"JSXOpeningElement","start":2452,"end":2681,"loc":{"start":{"line":23,"column":6},"end":{"line":23,"column":235}},"attributes":[{"type":"JSXAttribute","start":2458,"end":2678,"loc":{"start":{"line":23,"column":12},"end":{"line":23,"column":232}},"name":{"type":"JSXIdentifier","start":2458,"end":2459,"loc":{"start":{"line":23,"column":12},"end":{"line":23,"column":13}},"name":"d"},"value":{"type":"Literal","start":2460,"end":2678,"loc":{"start":{"line":23,"column":14},"end":{"line":23,"column":232}},"value":"M57 6H1a1 1 0 0 0-1 1v44a1 1 0 0 0 1 1h56a1 1 0 0 0 1-1V7a1 1 0 0 0-1-1zM10 28H2v-9h8v9zm-8 2h8v9H2v-9zm10 10V8h34v42H12V40zm44-12h-8v-9h8v9zm-8 2h8v9h-8v-9zm8-22v9h-8V8h8zM2 8h8v9H2V8zm0 42v-9h8v9H2zm54 0h-8v-9h8v9z","raw":"\"M57 6H1a1 1 0 0 0-1 1v44a1 1 0 0 0 1 1h56a1 1 0 0 0 1-1V7a1 1 0 0 0-1-1zM10 28H2v-9h8v9zm-8 2h8v9H2v-9zm10 10V8h34v42H12V40zm44-12h-8v-9h8v9zm-8 2h8v9h-8v-9zm8-22v9h-8V8h8zM2 8h8v9H2V8zm0 42v-9h8v9H2zm54 0h-8v-9h8v9z\""}}],"name":{"type":"JSXIdentifier","start":2453,"end":2457,"loc":{"start":{"line":23,"column":7},"end":{"line":23,"column":11}},"name":"path"},"selfClosing":true},"closingElement":null,"children":[]},{"type":"JSXText","start":2681,"end":2686,"loc":{"start":{"line":23,"column":235},"end":{"line":24,"column":4}},"value":"\n    ","raw":"\n    "}]}}]}},{"type":"ExpressionStatement","start":2700,"end":3010,"loc":{"start":{"line":28,"column":0},"end":{"line":41,"column":1}},"expression":{"type":"AssignmentExpression","start":2700,"end":3010,"loc":{"start":{"line":28,"column":0},"end":{"line":41,"column":1}},"operator":"=","left":{"type":"MemberExpression","start":2700,"end":2714,"loc":{"start":{"line":28,"column":0},"end":{"line":28,"column":14}},"object":{"type":"Identifier","start":2700,"end":2706,"loc":{"start":{"line":28,"column":0},"end":{"line":28,"column":6}},"name":"module"},"property":{"type":"Identifier","start":2707,"end":2714,"loc":{"start":{"line":28,"column":7},"end":{"line":28,"column":14}},"name":"exports"},"computed":false},"right":{"type":"ArrowFunctionExpression","start":2717,"end":3010,"loc":{"start":{"line":28,"column":17},"end":{"line":41,"column":1}},"id":null,"expression":false,"generator":false,"async":false,"params":[{"type":"Identifier","start":2718,"end":2723,"loc":{"start":{"line":28,"column":18},"end":{"line":28,"column":23}},"name":"props"}],"body":{"type":"BlockStatement","start":2728,"end":3010,"loc":{"start":{"line":28,"column":28},"end":{"line":41,"column":1}},"body":[{"type":"IfStatement","start":2732,"end":2773,"loc":{"start":{"line":29,"column":2},"end":{"line":29,"column":43}},"test":{"type":"BinaryExpression","start":2736,"end":2765,"loc":{"start":{"line":29,"column":6},"end":{"line":29,"column":35}},"left":{"type":"MemberExpression","start":2736,"end":2756,"loc":{"start":{"line":29,"column":6},"end":{"line":29,"column":26}},"object":{"type":"Identifier","start":2736,"end":2741,"loc":{"start":{"line":29,"column":6},"end":{"line":29,"column":11}},"name":"props"},"property":{"type":"Identifier","start":2742,"end":2756,"loc":{"start":{"line":29,"column":12},"end":{"line":29,"column":26}},"name":"itemIconString"},"computed":false},"operator":"===","right":{"type":"Literal","start":2761,"end":2765,"loc":{"start":{"line":29,"column":31},"end":{"line":29,"column":35}},"value":null,"raw":"null"}},"consequent":{"type":"ReturnStatement","start":2767,"end":2773,"loc":{"start":{"line":29,"column":37},"end":{"line":29,"column":43}},"argument":null},"alternate":null},{"type":"SwitchStatement","start":2777,"end":3008,"loc":{"start":{"line":31,"column":2},"end":{"line":40,"column":3}},"discriminant":{"type":"MemberExpression","start":2785,"end":2805,"loc":{"start":{"line":31,"column":10},"end":{"line":31,"column":30}},"object":{"type":"Identifier","start":2785,"end":2790,"loc":{"start":{"line":31,"column":10},"end":{"line":31,"column":15}},"name":"props"},"property":{"type":"Identifier","start":2791,"end":2805,"loc":{"start":{"line":31,"column":16},"end":{"line":31,"column":30}},"name":"itemIconString"},"computed":false},"cases":[{"type":"SwitchCase","start":2813,"end":2851,"loc":{"start":{"line":32,"column":4},"end":{"line":33,"column":25}},"consequent":[{"type":"ReturnStatement","start":2832,"end":2851,"loc":{"start":{"line":33,"column":6},"end":{"line":33,"column":25}},"argument":{"type":"JSXElement","start":2839,"end":2851,"loc":{"start":{"line":33,"column":13},"end":{"line":33,"column":25}},"openingElement":{"type":"JSXOpeningElement","start":2839,"end":2851,"loc":{"start":{"line":33,"column":13},"end":{"line":33,"column":25}},"attributes":[],"name":{"type":"JSXIdentifier","start":2840,"end":2848,"loc":{"start":{"line":33,"column":14},"end":{"line":33,"column":22}},"name":"FileIcon"},"selfClosing":true},"closingElement":null,"children":[]}}],"test":{"type":"Literal","start":2818,"end":2824,"loc":{"start":{"line":32,"column":9},"end":{"line":32,"column":15}},"value":"file","raw":"'file'"}},{"type":"SwitchCase","start":2856,"end":2898,"loc":{"start":{"line":34,"column":4},"end":{"line":35,"column":27}},"consequent":[{"type":"ReturnStatement","start":2877,"end":2898,"loc":{"start":{"line":35,"column":6},"end":{"line":35,"column":27}},"argument":{"type":"JSXElement","start":2884,"end":2898,"loc":{"start":{"line":35,"column":13},"end":{"line":35,"column":27}},"openingElement":{"type":"JSXOpeningElement","start":2884,"end":2898,"loc":{"start":{"line":35,"column":13},"end":{"line":35,"column":27}},"attributes":[],"name":{"type":"JSXIdentifier","start":2885,"end":2895,"loc":{"start":{"line":35,"column":14},"end":{"line":35,"column":24}},"name":"FolderIcon"},"selfClosing":true},"closingElement":null,"children":[]}}],"test":{"type":"Literal","start":2861,"end":2869,"loc":{"start":{"line":34,"column":9},"end":{"line":34,"column":17}},"value":"folder","raw":"'folder'"}},{"type":"SwitchCase","start":2903,"end":2943,"loc":{"start":{"line":36,"column":4},"end":{"line":37,"column":26}},"consequent":[{"type":"ReturnStatement","start":2923,"end":2943,"loc":{"start":{"line":37,"column":6},"end":{"line":37,"column":26}},"argument":{"type":"JSXElement","start":2930,"end":2943,"loc":{"start":{"line":37,"column":13},"end":{"line":37,"column":26}},"openingElement":{"type":"JSXOpeningElement","start":2930,"end":2943,"loc":{"start":{"line":37,"column":13},"end":{"line":37,"column":26}},"attributes":[],"name":{"type":"JSXIdentifier","start":2931,"end":2940,"loc":{"start":{"line":37,"column":14},"end":{"line":37,"column":23}},"name":"VideoIcon"},"selfClosing":true},"closingElement":null,"children":[]}}],"test":{"type":"Literal","start":2908,"end":2915,"loc":{"start":{"line":36,"column":9},"end":{"line":36,"column":16}},"value":"video","raw":"'video'"}},{"type":"SwitchCase","start":2948,"end":3004,"loc":{"start":{"line":38,"column":4},"end":{"line":39,"column":47}},"consequent":[{"type":"ReturnStatement","start":2963,"end":3004,"loc":{"start":{"line":39,"column":6},"end":{"line":39,"column":47}},"argument":{"type":"JSXElement","start":2970,"end":3004,"loc":{"start":{"line":39,"column":13},"end":{"line":39,"column":47}},"openingElement":{"type":"JSXOpeningElement","start":2970,"end":3004,"loc":{"start":{"line":39,"column":13},"end":{"line":39,"column":47}},"attributes":[{"type":"JSXAttribute","start":2975,"end":3001,"loc":{"start":{"line":39,"column":18},"end":{"line":39,"column":44}},"name":{"type":"JSXIdentifier","start":2975,"end":2978,"loc":{"start":{"line":39,"column":18},"end":{"line":39,"column":21}},"name":"src"},"value":{"type":"JSXExpressionContainer","start":2979,"end":3001,"loc":{"start":{"line":39,"column":22},"end":{"line":39,"column":44}},"expression":{"type":"MemberExpression","start":2980,"end":3000,"loc":{"start":{"line":39,"column":23},"end":{"line":39,"column":43}},"object":{"type":"Identifier","start":2980,"end":2985,"loc":{"start":{"line":39,"column":23},"end":{"line":39,"column":28}},"name":"props"},"property":{"type":"Identifier","start":2986,"end":3000,"loc":{"start":{"line":39,"column":29},"end":{"line":39,"column":43}},"name":"itemIconString"},"computed":false}}}],"name":{"type":"JSXIdentifier","start":2971,"end":2974,"loc":{"start":{"line":39,"column":14},"end":{"line":39,"column":17}},"name":"img"},"selfClosing":true},"closingElement":null,"children":[]}}],"test":null}]}]}}}}],"sourceType":"script"}