{"type":"Program","start":0,"end":3033,"body":[{"type":"FunctionDeclaration","start":0,"end":317,"id":{"type":"Identifier","start":9,"end":17,"name":"_extends"},"expression":false,"generator":false,"async":false,"params":[],"body":{"type":"BlockStatement","start":20,"end":317,"body":[{"type":"ExpressionStatement","start":22,"end":275,"expression":{"type":"AssignmentExpression","start":22,"end":274,"operator":"=","left":{"type":"Identifier","start":22,"end":30,"name":"_extends"},"right":{"type":"LogicalExpression","start":33,"end":274,"left":{"type":"MemberExpression","start":33,"end":46,"object":{"type":"Identifier","start":33,"end":39,"name":"Object"},"property":{"type":"Identifier","start":40,"end":46,"name":"assign"},"computed":false},"operator":"||","right":{"type":"FunctionExpression","start":50,"end":274,"id":null,"expression":false,"generator":false,"async":false,"params":[{"type":"Identifier","start":60,"end":66,"name":"target"}],"body":{"type":"BlockStatement","start":68,"end":274,"body":[{"type":"ForStatement","start":70,"end":257,"init":{"type":"VariableDeclaration","start":75,"end":84,"declarations":[{"type":"VariableDeclarator","start":79,"end":84,"id":{"type":"Identifier","start":79,"end":80,"name":"i"},"init":{"type":"Literal","start":83,"end":84,"value":1,"raw":"1"}}],"kind":"var"},"test":{"type":"BinaryExpression","start":86,"end":106,"left":{"type":"Identifier","start":86,"end":87,"name":"i"},"operator":"<","right":{"type":"MemberExpression","start":90,"end":106,"object":{"type":"Identifier","start":90,"end":99,"name":"arguments"},"property":{"type":"Identifier","start":100,"end":106,"name":"length"},"computed":false}},"update":{"type":"UpdateExpression","start":108,"end":111,"operator":"++","prefix":false,"argument":{"type":"Identifier","start":108,"end":109,"name":"i"}},"body":{"type":"BlockStatement","start":113,"end":257,"body":[{"type":"VariableDeclaration","start":115,"end":141,"declarations":[{"type":"VariableDeclarator","start":119,"end":140,"id":{"type":"Identifier","start":119,"end":125,"name":"source"},"init":{"type":"MemberExpression","start":128,"end":140,"object":{"type":"Identifier","start":128,"end":137,"name":"arguments"},"property":{"type":"Identifier","start":138,"end":139,"name":"i"},"computed":true}}],"kind":"var"},{"type":"ForInStatement","start":142,"end":255,"left":{"type":"VariableDeclaration","start":147,"end":154,"declarations":[{"type":"VariableDeclarator","start":151,"end":154,"id":{"type":"Identifier","start":151,"end":154,"name":"key"},"init":null}],"kind":"var"},"right":{"type":"Identifier","start":158,"end":164,"name":"source"},"body":{"type":"BlockStatement","start":166,"end":255,"body":[{"type":"IfStatement","start":168,"end":253,"test":{"type":"CallExpression","start":172,"end":221,"callee":{"type":"MemberExpression","start":172,"end":208,"object":{"type":"MemberExpression","start":172,"end":203,"object":{"type":"MemberExpression","start":172,"end":188,"object":{"type":"Identifier","start":172,"end":178,"name":"Object"},"property":{"type":"Identifier","start":179,"end":188,"name":"prototype"},"computed":false},"property":{"type":"Identifier","start":189,"end":203,"name":"hasOwnProperty"},"computed":false},"property":{"type":"Identifier","start":204,"end":208,"name":"call"},"computed":false},"arguments":[{"type":"Identifier","start":209,"end":215,"name":"source"},{"type":"Identifier","start":217,"end":220,"name":"key"}]},"consequent":{"type":"BlockStatement","start":223,"end":253,"body":[{"type":"ExpressionStatement","start":225,"end":251,"expression":{"type":"AssignmentExpression","start":225,"end":250,"operator":"=","left":{"type":"MemberExpression","start":225,"end":236,"object":{"type":"Identifier","start":225,"end":231,"name":"target"},"property":{"type":"Identifier","start":232,"end":235,"name":"key"},"computed":true},"right":{"type":"MemberExpression","start":239,"end":250,"object":{"type":"Identifier","start":239,"end":245,"name":"source"},"property":{"type":"Identifier","start":246,"end":249,"name":"key"},"computed":true}}}]},"alternate":null}]}}]}},{"type":"ReturnStatement","start":258,"end":272,"argument":{"type":"Identifier","start":265,"end":271,"name":"target"}}]}}}}},{"type":"ReturnStatement","start":276,"end":315,"argument":{"type":"CallExpression","start":283,"end":314,"callee":{"type":"MemberExpression","start":283,"end":297,"object":{"type":"Identifier","start":283,"end":291,"name":"_extends"},"property":{"type":"Identifier","start":292,"end":297,"name":"apply"},"computed":false},"arguments":[{"type":"ThisExpression","start":298,"end":302},{"type":"Identifier","start":304,"end":313,"name":"arguments"}]}}]}},{"type":"VariableDeclaration","start":319,"end":346,"declarations":[{"type":"VariableDeclarator","start":323,"end":345,"id":{"type":"Identifier","start":323,"end":327,"name":"cuid"},"init":{"type":"CallExpression","start":330,"end":345,"callee":{"type":"Identifier","start":330,"end":337,"name":"require"},"arguments":[{"type":"Literal","start":338,"end":344,"value":"cuid","raw":"'cuid'"}]}}],"kind":"var"},{"type":"VariableDeclaration","start":371,"end":410,"declarations":[{"type":"VariableDeclarator","start":375,"end":409,"id":{"type":"Identifier","start":375,"end":387,"name":"STATE_UPDATE"},"init":{"type":"Literal","start":390,"end":409,"value":"uppy/STATE_UPDATE","raw":"'uppy/STATE_UPDATE'"}}],"kind":"var"},{"type":"VariableDeclaration","start":478,"end":593,"declarations":[{"type":"VariableDeclarator","start":482,"end":592,"id":{"type":"Identifier","start":482,"end":497,"name":"defaultSelector"},"init":{"type":"FunctionExpression","start":500,"end":592,"id":{"type":"Identifier","start":509,"end":524,"name":"defaultSelector"},"expression":false,"generator":false,"async":false,"params":[{"type":"Identifier","start":525,"end":527,"name":"id"}],"body":{"type":"BlockStatement","start":529,"end":592,"body":[{"type":"ReturnStatement","start":533,"end":590,"argument":{"type":"FunctionExpression","start":540,"end":589,"id":null,"expression":false,"generator":false,"async":false,"params":[{"type":"Identifier","start":550,"end":555,"name":"state"}],"body":{"type":"BlockStatement","start":557,"end":589,"body":[{"type":"ReturnStatement","start":563,"end":585,"argument":{"type":"MemberExpression","start":570,"end":584,"object":{"type":"MemberExpression","start":570,"end":580,"object":{"type":"Identifier","start":570,"end":575,"name":"state"},"property":{"type":"Identifier","start":576,"end":580,"name":"uppy"},"computed":false},"property":{"type":"Identifier","start":581,"end":583,"name":"id"},"computed":true}}]}}}]}}}],"kind":"var"},{"type":"VariableDeclaration","start":1098,"end":2064,"declarations":[{"type":"VariableDeclarator","start":1102,"end":2063,"id":{"type":"Identifier","start":1102,"end":1112,"name":"ReduxStore"},"init":{"type":"CallExpression","start":1128,"end":2063,"callee":{"type":"FunctionExpression","start":1128,"end":2061,"id":null,"expression":false,"generator":false,"async":false,"params":[],"body":{"type":"BlockStatement","start":1140,"end":2061,"body":[{"type":"FunctionDeclaration","start":1144,"end":1368,"id":{"type":"Identifier","start":1153,"end":1163,"name":"ReduxStore"},"expression":false,"generator":false,"async":false,"params":[{"type":"Identifier","start":1164,"end":1168,"name":"opts"}],"body":{"type":"BlockStatement","start":1170,"end":1368,"body":[{"type":"ExpressionStatement","start":1176,"end":1201,"expression":{"type":"AssignmentExpression","start":1176,"end":1200,"operator":"=","left":{"type":"MemberExpression","start":1176,"end":1187,"object":{"type":"ThisExpression","start":1176,"end":1180},"property":{"type":"Identifier","start":1181,"end":1187,"name":"_store"},"computed":false},"right":{"type":"MemberExpression","start":1190,"end":1200,"object":{"type":"Identifier","start":1190,"end":1194,"name":"opts"},"property":{"type":"Identifier","start":1195,"end":1200,"name":"store"},"computed":false}}},{"type":"ExpressionStatement","start":1206,"end":1235,"expression":{"type":"AssignmentExpression","start":1206,"end":1234,"operator":"=","left":{"type":"MemberExpression","start":1206,"end":1214,"object":{"type":"ThisExpression","start":1206,"end":1210},"property":{"type":"Identifier","start":1211,"end":1214,"name":"_id"},"computed":false},"right":{"type":"LogicalExpression","start":1217,"end":1234,"left":{"type":"MemberExpression","start":1217,"end":1224,"object":{"type":"Identifier","start":1217,"end":1221,"name":"opts"},"property":{"type":"Identifier","start":1222,"end":1224,"name":"id"},"computed":false},"operator":"||","right":{"type":"CallExpression","start":1228,"end":1234,"callee":{"type":"Identifier","start":1228,"end":1232,"name":"cuid"},"arguments":[]}}}},{"type":"ExpressionStatement","start":1240,"end":1300,"expression":{"type":"AssignmentExpression","start":1240,"end":1299,"operator":"=","left":{"type":"MemberExpression","start":1240,"end":1254,"object":{"type":"ThisExpression","start":1240,"end":1244},"property":{"type":"Identifier","start":1245,"end":1254,"name":"_selector"},"computed":false},"right":{"type":"LogicalExpression","start":1257,"end":1299,"left":{"type":"MemberExpression","start":1257,"end":1270,"object":{"type":"Identifier","start":1257,"end":1261,"name":"opts"},"property":{"type":"Identifier","start":1262,"end":1270,"name":"selector"},"computed":false},"operator":"||","right":{"type":"CallExpression","start":1274,"end":1299,"callee":{"type":"Identifier","start":1274,"end":1289,"name":"defaultSelector"},"arguments":[{"type":"MemberExpression","start":1290,"end":1298,"object":{"type":"ThisExpression","start":1290,"end":1294},"property":{"type":"Identifier","start":1295,"end":1298,"name":"_id"},"computed":false}]}}}},{"type":"ExpressionStatement","start":1346,"end":1364,"expression":{"type":"CallExpression","start":1346,"end":1363,"callee":{"type":"MemberExpression","start":1346,"end":1359,"object":{"type":"ThisExpression","start":1346,"end":1350},"property":{"type":"Identifier","start":1351,"end":1359,"name":"setState"},"computed":false},"arguments":[{"type":"ObjectExpression","start":1360,"end":1362,"properties":[]}]}}]}},{"type":"VariableDeclaration","start":1372,"end":1406,"declarations":[{"type":"VariableDeclarator","start":1376,"end":1405,"id":{"type":"Identifier","start":1376,"end":1382,"name":"_proto"},"init":{"type":"MemberExpression","start":1385,"end":1405,"object":{"type":"Identifier","start":1385,"end":1395,"name":"ReduxStore"},"property":{"type":"Identifier","start":1396,"end":1405,"name":"prototype"},"computed":false}}],"kind":"var"},{"type":"ExpressionStatement","start":1410,"end":1561,"expression":{"type":"AssignmentExpression","start":1410,"end":1560,"operator":"=","left":{"type":"MemberExpression","start":1410,"end":1425,"object":{"type":"Identifier","start":1410,"end":1416,"name":"_proto"},"property":{"type":"Identifier","start":1417,"end":1425,"name":"setState"},"computed":false},"right":{"type":"FunctionExpression","start":1428,"end":1560,"id":{"type":"Identifier","start":1437,"end":1445,"name":"setState"},"expression":false,"generator":false,"async":false,"params":[{"type":"Identifier","start":1446,"end":1451,"name":"patch"}],"body":{"type":"BlockStatement","start":1453,"end":1560,"body":[{"type":"ExpressionStatement","start":1459,"end":1556,"expression":{"type":"CallExpression","start":1459,"end":1555,"callee":{"type":"MemberExpression","start":1459,"end":1479,"object":{"type":"MemberExpression","start":1459,"end":1470,"object":{"type":"ThisExpression","start":1459,"end":1463},"property":{"type":"Identifier","start":1464,"end":1470,"name":"_store"},"computed":false},"property":{"type":"Identifier","start":1471,"end":1479,"name":"dispatch"},"computed":false},"arguments":[{"type":"ObjectExpression","start":1480,"end":1554,"properties":[{"type":"Property","start":1488,"end":1506,"method":false,"shorthand":false,"computed":false,"key":{"type":"Identifier","start":1488,"end":1492,"name":"type"},"value":{"type":"Identifier","start":1494,"end":1506,"name":"STATE_UPDATE"},"kind":"init"},{"type":"Property","start":1514,"end":1526,"method":false,"shorthand":false,"computed":false,"key":{"type":"Identifier","start":1514,"end":1516,"name":"id"},"value":{"type":"MemberExpression","start":1518,"end":1526,"object":{"type":"ThisExpression","start":1518,"end":1522},"property":{"type":"Identifier","start":1523,"end":1526,"name":"_id"},"computed":false},"kind":"init"},{"type":"Property","start":1534,"end":1548,"method":false,"shorthand":false,"computed":false,"key":{"type":"Identifier","start":1534,"end":1541,"name":"payload"},"value":{"type":"Identifier","start":1543,"end":1548,"name":"patch"},"kind":"init"}]}]}}]}}}},{"type":"ExpressionStatement","start":1565,"end":1660,"expression":{"type":"AssignmentExpression","start":1565,"end":1659,"operator":"=","left":{"type":"MemberExpression","start":1565,"end":1580,"object":{"type":"Identifier","start":1565,"end":1571,"name":"_proto"},"property":{"type":"Identifier","start":1572,"end":1580,"name":"getState"},"computed":false},"right":{"type":"FunctionExpression","start":1583,"end":1659,"id":{"type":"Identifier","start":1592,"end":1600,"name":"getState"},"expression":false,"generator":false,"async":false,"params":[],"body":{"type":"BlockStatement","start":1603,"end":1659,"body":[{"type":"ReturnStatement","start":1609,"end":1655,"argument":{"type":"CallExpression","start":1616,"end":1654,"callee":{"type":"MemberExpression","start":1616,"end":1630,"object":{"type":"ThisExpression","start":1616,"end":1620},"property":{"type":"Identifier","start":1621,"end":1630,"name":"_selector"},"computed":false},"arguments":[{"type":"CallExpression","start":1631,"end":1653,"callee":{"type":"MemberExpression","start":1631,"end":1651,"object":{"type":"MemberExpression","start":1631,"end":1642,"object":{"type":"ThisExpression","start":1631,"end":1635},"property":{"type":"Identifier","start":1636,"end":1642,"name":"_store"},"computed":false},"property":{"type":"Identifier","start":1643,"end":1651,"name":"getState"},"computed":false},"arguments":[]}]}}]}}}},{"type":"ExpressionStatement","start":1664,"end":2037,"expression":{"type":"AssignmentExpression","start":1664,"end":2036,"operator":"=","left":{"type":"MemberExpression","start":1664,"end":1680,"object":{"type":"Identifier","start":1664,"end":1670,"name":"_proto"},"property":{"type":"Identifier","start":1671,"end":1680,"name":"subscribe"},"computed":false},"right":{"type":"FunctionExpression","start":1683,"end":2036,"id":{"type":"Identifier","start":1692,"end":1701,"name":"subscribe"},"expression":false,"generator":false,"async":false,"params":[{"type":"Identifier","start":1702,"end":1704,"name":"cb"}],"body":{"type":"BlockStatement","start":1706,"end":2036,"body":[{"type":"VariableDeclaration","start":1712,"end":1729,"declarations":[{"type":"VariableDeclarator","start":1716,"end":1728,"id":{"type":"Identifier","start":1716,"end":1721,"name":"_this"},"init":{"type":"ThisExpression","start":1724,"end":1728}}],"kind":"var"},{"type":"VariableDeclaration","start":1735,"end":1767,"declarations":[{"type":"VariableDeclarator","start":1739,"end":1766,"id":{"type":"Identifier","start":1739,"end":1748,"name":"prevState"},"init":{"type":"CallExpression","start":1751,"end":1766,"callee":{"type":"MemberExpression","start":1751,"end":1764,"object":{"type":"ThisExpression","start":1751,"end":1755},"property":{"type":"Identifier","start":1756,"end":1764,"name":"getState"},"computed":false},"arguments":[]}}],"kind":"var"},{"type":"ReturnStatement","start":1772,"end":2032,"argument":{"type":"CallExpression","start":1779,"end":2031,"callee":{"type":"MemberExpression","start":1779,"end":1800,"object":{"type":"MemberExpression","start":1779,"end":1790,"object":{"type":"ThisExpression","start":1779,"end":1783},"property":{"type":"Identifier","start":1784,"end":1790,"name":"_store"},"computed":false},"property":{"type":"Identifier","start":1791,"end":1800,"name":"subscribe"},"computed":false},"arguments":[{"type":"FunctionExpression","start":1801,"end":2030,"id":null,"expression":false,"generator":false,"async":false,"params":[],"body":{"type":"BlockStatement","start":1813,"end":2030,"body":[{"type":"VariableDeclaration","start":1821,"end":1854,"declarations":[{"type":"VariableDeclarator","start":1825,"end":1853,"id":{"type":"Identifier","start":1825,"end":1834,"name":"nextState"},"init":{"type":"CallExpression","start":1837,"end":1853,"callee":{"type":"MemberExpression","start":1837,"end":1851,"object":{"type":"Identifier","start":1837,"end":1842,"name":"_this"},"property":{"type":"Identifier","start":1843,"end":1851,"name":"getState"},"computed":false},"arguments":[]}}],"kind":"var"},{"type":"IfStatement","start":1862,"end":2024,"test":{"type":"BinaryExpression","start":1866,"end":1889,"left":{"type":"Identifier","start":1866,"end":1875,"name":"prevState"},"operator":"!==","right":{"type":"Identifier","start":1880,"end":1889,"name":"nextState"}},"consequent":{"type":"BlockStatement","start":1891,"end":2024,"body":[{"type":"VariableDeclaration","start":1901,"end":1944,"declarations":[{"type":"VariableDeclarator","start":1905,"end":1943,"id":{"type":"Identifier","start":1905,"end":1910,"name":"patch"},"init":{"type":"CallExpression","start":1913,"end":1943,"callee":{"type":"Identifier","start":1913,"end":1921,"name":"getPatch"},"arguments":[{"type":"Identifier","start":1922,"end":1931,"name":"prevState"},{"type":"Identifier","start":1933,"end":1942,"name":"nextState"}]}}],"kind":"var"},{"type":"ExpressionStatement","start":1953,"end":1985,"expression":{"type":"CallExpression","start":1953,"end":1984,"callee":{"type":"Identifier","start":1953,"end":1955,"name":"cb"},"arguments":[{"type":"Identifier","start":1956,"end":1965,"name":"prevState"},{"type":"Identifier","start":1967,"end":1976,"name":"nextState"},{"type":"Identifier","start":1978,"end":1983,"name":"patch"}]}},{"type":"ExpressionStatement","start":1994,"end":2016,"expression":{"type":"AssignmentExpression","start":1994,"end":2015,"operator":"=","left":{"type":"Identifier","start":1994,"end":2003,"name":"prevState"},"right":{"type":"Identifier","start":2006,"end":2015,"name":"nextState"}}}]},"alternate":null}]}}]}}]}}}},{"type":"ReturnStatement","start":2041,"end":2059,"argument":{"type":"Identifier","start":2048,"end":2058,"name":"ReduxStore"}}]}},"arguments":[]}}],"kind":"var"},{"type":"ExpressionStatement","start":2066,"end":2122,"expression":{"type":"AssignmentExpression","start":2066,"end":2121,"operator":"=","left":{"type":"MemberExpression","start":2066,"end":2084,"object":{"type":"Identifier","start":2066,"end":2076,"name":"ReduxStore"},"property":{"type":"Identifier","start":2077,"end":2084,"name":"VERSION"},"computed":false},"right":{"type":"MemberExpression","start":2087,"end":2121,"object":{"type":"CallExpression","start":2087,"end":2113,"callee":{"type":"Identifier","start":2087,"end":2094,"name":"require"},"arguments":[{"type":"Literal","start":2095,"end":2112,"value":"../package.json","raw":"'../package.json'"}]},"property":{"type":"Identifier","start":2114,"end":2121,"name":"version"},"computed":false}}},{"type":"FunctionDeclaration","start":2124,"end":2316,"id":{"type":"Identifier","start":2133,"end":2141,"name":"getPatch"},"expression":false,"generator":false,"async":false,"params":[{"type":"Identifier","start":2142,"end":2146,"name":"prev"},{"type":"Identifier","start":2148,"end":2152,"name":"next"}],"body":{"type":"BlockStatement","start":2154,"end":2316,"body":[{"type":"VariableDeclaration","start":2158,"end":2191,"declarations":[{"type":"VariableDeclarator","start":2162,"end":2190,"id":{"type":"Identifier","start":2162,"end":2170,"name":"nextKeys"},"init":{"type":"CallExpression","start":2173,"end":2190,"callee":{"type":"MemberExpression","start":2173,"end":2184,"object":{"type":"Identifier","start":2173,"end":2179,"name":"Object"},"property":{"type":"Identifier","start":2180,"end":2184,"name":"keys"},"computed":false},"arguments":[{"type":"Identifier","start":2185,"end":2189,"name":"next"}]}}],"kind":"var"},{"type":"VariableDeclaration","start":2194,"end":2209,"declarations":[{"type":"VariableDeclarator","start":2198,"end":2208,"id":{"type":"Identifier","start":2198,"end":2203,"name":"patch"},"init":{"type":"ObjectExpression","start":2206,"end":2208,"properties":[]}}],"kind":"var"},{"type":"ExpressionStatement","start":2212,"end":2298,"expression":{"type":"CallExpression","start":2212,"end":2297,"callee":{"type":"MemberExpression","start":2212,"end":2228,"object":{"type":"Identifier","start":2212,"end":2220,"name":"nextKeys"},"property":{"type":"Identifier","start":2221,"end":2228,"name":"forEach"},"computed":false},"arguments":[{"type":"FunctionExpression","start":2229,"end":2296,"id":null,"expression":false,"generator":false,"async":false,"params":[{"type":"Identifier","start":2239,"end":2240,"name":"k"}],"body":{"type":"BlockStatement","start":2242,"end":2296,"body":[{"type":"IfStatement","start":2248,"end":2292,"test":{"type":"BinaryExpression","start":2252,"end":2271,"left":{"type":"MemberExpression","start":2252,"end":2259,"object":{"type":"Identifier","start":2252,"end":2256,"name":"prev"},"property":{"type":"Identifier","start":2257,"end":2258,"name":"k"},"computed":true},"operator":"!==","right":{"type":"MemberExpression","start":2264,"end":2271,"object":{"type":"Identifier","start":2264,"end":2268,"name":"next"},"property":{"type":"Identifier","start":2269,"end":2270,"name":"k"},"computed":true}},"consequent":{"type":"ExpressionStatement","start":2273,"end":2292,"expression":{"type":"AssignmentExpression","start":2273,"end":2291,"operator":"=","left":{"type":"MemberExpression","start":2273,"end":2281,"object":{"type":"Identifier","start":2273,"end":2278,"name":"patch"},"property":{"type":"Identifier","start":2279,"end":2280,"name":"k"},"computed":true},"right":{"type":"MemberExpression","start":2284,"end":2291,"object":{"type":"Identifier","start":2284,"end":2288,"name":"next"},"property":{"type":"Identifier","start":2289,"end":2290,"name":"k"},"computed":true}}},"alternate":null}]}}]}},{"type":"ReturnStatement","start":2301,"end":2314,"argument":{"type":"Identifier","start":2308,"end":2313,"name":"patch"}}]}},{"type":"FunctionDeclaration","start":2318,"end":2641,"id":{"type":"Identifier","start":2327,"end":2334,"name":"reducer"},"expression":false,"generator":false,"async":false,"params":[{"type":"Identifier","start":2335,"end":2340,"name":"state"},{"type":"Identifier","start":2342,"end":2348,"name":"action"}],"body":{"type":"BlockStatement","start":2350,"end":2641,"body":[{"type":"IfStatement","start":2354,"end":2397,"test":{"type":"BinaryExpression","start":2358,"end":2374,"left":{"type":"Identifier","start":2358,"end":2363,"name":"state"},"operator":"===","right":{"type":"UnaryExpression","start":2368,"end":2374,"operator":"void","prefix":true,"argument":{"type":"Literal","start":2373,"end":2374,"value":0,"raw":"0"}}},"consequent":{"type":"BlockStatement","start":2376,"end":2397,"body":[{"type":"ExpressionStatement","start":2382,"end":2393,"expression":{"type":"AssignmentExpression","start":2382,"end":2392,"operator":"=","left":{"type":"Identifier","start":2382,"end":2387,"name":"state"},"right":{"type":"ObjectExpression","start":2390,"end":2392,"properties":[]}}}]},"alternate":null},{"type":"IfStatement","start":2401,"end":2622,"test":{"type":"BinaryExpression","start":2405,"end":2433,"left":{"type":"MemberExpression","start":2405,"end":2416,"object":{"type":"Identifier","start":2405,"end":2411,"name":"action"},"property":{"type":"Identifier","start":2412,"end":2416,"name":"type"},"computed":false},"operator":"===","right":{"type":"Identifier","start":2421,"end":2433,"name":"STATE_UPDATE"}},"consequent":{"type":"BlockStatement","start":2435,"end":2622,"body":[{"type":"VariableDeclaration","start":2441,"end":2455,"declarations":[{"type":"VariableDeclarator","start":2445,"end":2454,"id":{"type":"Identifier","start":2445,"end":2454,"name":"_extends2"},"init":null}],"kind":"var"},{"type":"VariableDeclaration","start":2461,"end":2523,"declarations":[{"type":"VariableDeclarator","start":2465,"end":2522,"id":{"type":"Identifier","start":2465,"end":2473,"name":"newState"},"init":{"type":"CallExpression","start":2476,"end":2522,"callee":{"type":"Identifier","start":2476,"end":2484,"name":"_extends"},"arguments":[{"type":"ObjectExpression","start":2485,"end":2487,"properties":[]},{"type":"MemberExpression","start":2489,"end":2505,"object":{"type":"Identifier","start":2489,"end":2494,"name":"state"},"property":{"type":"MemberExpression","start":2495,"end":2504,"object":{"type":"Identifier","start":2495,"end":2501,"name":"action"},"property":{"type":"Identifier","start":2502,"end":2504,"name":"id"},"computed":false},"computed":true},{"type":"MemberExpression","start":2507,"end":2521,"object":{"type":"Identifier","start":2507,"end":2513,"name":"action"},"property":{"type":"Identifier","start":2514,"end":2521,"name":"payload"},"computed":false}]}}],"kind":"var"},{"type":"ReturnStatement","start":2529,"end":2618,"argument":{"type":"CallExpression","start":2536,"end":2617,"callee":{"type":"Identifier","start":2536,"end":2544,"name":"_extends"},"arguments":[{"type":"ObjectExpression","start":2545,"end":2547,"properties":[]},{"type":"Identifier","start":2549,"end":2554,"name":"state"},{"type":"SequenceExpression","start":2557,"end":2615,"expressions":[{"type":"AssignmentExpression","start":2557,"end":2571,"operator":"=","left":{"type":"Identifier","start":2557,"end":2566,"name":"_extends2"},"right":{"type":"ObjectExpression","start":2569,"end":2571,"properties":[]}},{"type":"AssignmentExpression","start":2573,"end":2604,"operator":"=","left":{"type":"MemberExpression","start":2573,"end":2593,"object":{"type":"Identifier","start":2573,"end":2582,"name":"_extends2"},"property":{"type":"MemberExpression","start":2583,"end":2592,"object":{"type":"Identifier","start":2583,"end":2589,"name":"action"},"property":{"type":"Identifier","start":2590,"end":2592,"name":"id"},"computed":false},"computed":true},"right":{"type":"Identifier","start":2596,"end":2604,"name":"newState"}},{"type":"Identifier","start":2606,"end":2615,"name":"_extends2"}]}]}}]},"alternate":null},{"type":"ReturnStatement","start":2626,"end":2639,"argument":{"type":"Identifier","start":2633,"end":2638,"name":"state"}}]}},{"type":"FunctionDeclaration","start":2643,"end":2828,"id":{"type":"Identifier","start":2652,"end":2662,"name":"middleware"},"expression":false,"generator":false,"async":false,"params":[],"body":{"type":"BlockStatement","start":2665,"end":2828,"body":[{"type":"ReturnStatement","start":2701,"end":2826,"argument":{"type":"FunctionExpression","start":2708,"end":2825,"id":null,"expression":false,"generator":false,"async":false,"params":[],"body":{"type":"BlockStatement","start":2720,"end":2825,"body":[{"type":"ReturnStatement","start":2726,"end":2821,"argument":{"type":"FunctionExpression","start":2733,"end":2820,"id":null,"expression":false,"generator":false,"async":false,"params":[{"type":"Identifier","start":2743,"end":2747,"name":"next"}],"body":{"type":"BlockStatement","start":2749,"end":2820,"body":[{"type":"ReturnStatement","start":2757,"end":2814,"argument":{"type":"FunctionExpression","start":2764,"end":2813,"id":null,"expression":false,"generator":false,"async":false,"params":[{"type":"Identifier","start":2774,"end":2780,"name":"action"}],"body":{"type":"BlockStatement","start":2782,"end":2813,"body":[{"type":"ExpressionStatement","start":2792,"end":2805,"expression":{"type":"CallExpression","start":2792,"end":2804,"callee":{"type":"Identifier","start":2792,"end":2796,"name":"next"},"arguments":[{"type":"Identifier","start":2797,"end":2803,"name":"action"}]}}]}}}]}}}]}}}]}},{"type":"ExpressionStatement","start":2830,"end":2914,"expression":{"type":"AssignmentExpression","start":2830,"end":2913,"operator":"=","left":{"type":"MemberExpression","start":2830,"end":2844,"object":{"type":"Identifier","start":2830,"end":2836,"name":"module"},"property":{"type":"Identifier","start":2837,"end":2844,"name":"exports"},"computed":false},"right":{"type":"FunctionExpression","start":2847,"end":2913,"id":{"type":"Identifier","start":2856,"end":2872,"name":"createReduxStore"},"expression":false,"generator":false,"async":false,"params":[{"type":"Identifier","start":2873,"end":2877,"name":"opts"}],"body":{"type":"BlockStatement","start":2879,"end":2913,"body":[{"type":"ReturnStatement","start":2883,"end":2911,"argument":{"type":"NewExpression","start":2890,"end":2910,"callee":{"type":"Identifier","start":2894,"end":2904,"name":"ReduxStore"},"arguments":[{"type":"Identifier","start":2905,"end":2909,"name":"opts"}]}}]}}}},{"type":"ExpressionStatement","start":2916,"end":2959,"expression":{"type":"AssignmentExpression","start":2916,"end":2958,"operator":"=","left":{"type":"MemberExpression","start":2916,"end":2943,"object":{"type":"MemberExpression","start":2916,"end":2930,"object":{"type":"Identifier","start":2916,"end":2922,"name":"module"},"property":{"type":"Identifier","start":2923,"end":2930,"name":"exports"},"computed":false},"property":{"type":"Identifier","start":2931,"end":2943,"name":"STATE_UPDATE"},"computed":false},"right":{"type":"Identifier","start":2946,"end":2958,"name":"STATE_UPDATE"}}},{"type":"ExpressionStatement","start":2960,"end":2993,"expression":{"type":"AssignmentExpression","start":2960,"end":2992,"operator":"=","left":{"type":"MemberExpression","start":2960,"end":2982,"object":{"type":"MemberExpression","start":2960,"end":2974,"object":{"type":"Identifier","start":2960,"end":2966,"name":"module"},"property":{"type":"Identifier","start":2967,"end":2974,"name":"exports"},"computed":false},"property":{"type":"Identifier","start":2975,"end":2982,"name":"reducer"},"computed":false},"right":{"type":"Identifier","start":2985,"end":2992,"name":"reducer"}}},{"type":"ExpressionStatement","start":2994,"end":3033,"expression":{"type":"AssignmentExpression","start":2994,"end":3032,"operator":"=","left":{"type":"MemberExpression","start":2994,"end":3019,"object":{"type":"MemberExpression","start":2994,"end":3008,"object":{"type":"Identifier","start":2994,"end":3000,"name":"module"},"property":{"type":"Identifier","start":3001,"end":3008,"name":"exports"},"computed":false},"property":{"type":"Identifier","start":3009,"end":3019,"name":"middleware"},"computed":false},"right":{"type":"Identifier","start":3022,"end":3032,"name":"middleware"}}}],"sourceType":"script"}